imspect-0.1.3.dist-info/METADATA
imspect-0.1.3.dist-info/WHEEL
imspect-0.1.3.dist-info/entry_points.txt
imspect-0.1.3.dist-info/licenses/LICENSE
imspect/__init__.py
imspect/imspect.pyd
imspect-0.1.3.dist-info/RECORD
