Metadata-Version: 2.4
Name: imspect
Version: 0.1.3
Classifier: Programming Language :: Rust
Classifier: Programming Language :: Python :: Implementation :: CPython
License-File: LICENSE
Summary: Explore features of images during debug session
Keywords: images,cv,gui
Author: Sebrovskiy Konstantin, sebrovskiy.k@gmail.com
Author-email: SEBROVATER <sebrovskiy.k@gmail.com>
License: MIT
Requires-Python: >=3.8
Project-URL: github, https://github.com/SEBROVATER/imspect
